sbobet/__init__.py
sbobet/auth.py
sbobet/client.py
sbobet/exceptions.py
sbobet/settings.py
cc_sbobet-2.1.3.dist-info/METADATA
cc_sbobet-2.1.3.dist-info/WHEEL
cc_sbobet-2.1.3.dist-info/top_level.txt
cc_sbobet-2.1.3.dist-info/RECORD
