Metadata-Version: 2.1
Name: cc-sbobet
Version: 2.1.3
Author: 
Author-email: 
License: MIT
Requires-Python: >=3.7
Requires-Dist: requests
Requires-Dist: cc-api-helper
Requires-Dist: beautifulsoup4
Requires-Dist: PyJWT
